{
  "lastExecution": {
    "lastExecuted": "2023-12-20T10:46:19.916Z",
    "events": 0,
    "users": 0,
    "repos": 0
  },
  "checked": {
    "mojombo": {
      "owner": "mojombo",
      "lastExecuted": "2023-12-20T08:20:26.782Z"
    },
    "ry": {
      "owner": "ry",
      "lastExecuted": "2023-12-20T08:20:26.782Z"
    },
    "robbyrussell": {
      "owner": "robbyrussell",
      "lastExecuted": "2023-12-20T08:20:26.782Z"
    },
    "samaaron": {
      "owner": "samaaron",
      "lastExecuted": "2023-12-20T08:20:26.782Z"
    },
    "kangax": {
      "owner": "kangax",
      "lastExecuted": "2023-12-20T08:20:26.782Z"
    },
    "progrium": {
      "owner": "progrium",
      "lastExecuted": "2023-12-20T08:20:26.782Z"
    },
    "peters": {
      "owner": "peters",
      "lastExecuted": "2023-12-20T08:20:26.782Z"
    },
    "Sija": {
      "owner": "Sija",
      "lastExecuted": "2023-12-20T08:20:26.782Z"
    },
    "andrew": {
      "owner": "andrew",
      "lastExecuted": "2023-12-20T08:20:26.782Z"
    },
    "mitchellh": {
      "owner": "mitchellh",
      "lastExecuted": "2023-12-20T08:20:26.782Z"
    },
    "aemkei": {
      "owner": "aemkei",
      "lastExecuted": "2023-12-20T09:13:35.071Z"
    },
    "casey": {
      "owner": "casey",
      "lastExecuted": "2023-12-20T08:20:26.782Z"
    },
    "cheeaun": {
      "owner": "cheeaun",
      "lastExecuted": "2023-12-20T08:20:26.782Z"
    },
    "daeken": {
      "owner": "daeken",
      "lastExecuted": "2022-02-08T00:33:28.520Z"
    },
    "andymatuschak": {
      "owner": "andymatuschak",
      "lastExecuted": "2023-12-20T08:20:26.782Z"
    },
    "shanselman": {
      "owner": "shanselman",
      "lastExecuted": "2023-12-20T08:20:26.782Z"
    },
    "psychs": {
      "owner": "psychs",
      "lastExecuted": "2022-02-08T00:33:28.520Z"
    },
    "derailed": {
      "owner": "derailed",
      "lastExecuted": "2023-12-20T08:20:26.782Z"
    },
    "arfon": {
      "owner": "arfon",
      "lastExecuted": "2023-12-20T09:19:41.764Z"
    },
    "sergeyk": {
      "owner": "sergeyk",
      "lastExecuted": "2022-02-08T00:33:28.520Z"
    },
    "andreyvit": {
      "owner": "andreyvit",
      "lastExecuted": "2023-12-20T08:20:26.782Z"
    },
    "benjamn": {
      "owner": "benjamn",
      "lastExecuted": "2023-12-20T08:20:26.782Z"
    },
    "jasonlong": {
      "owner": "jasonlong",
      "lastExecuted": "2023-12-20T08:20:26.782Z"
    },
    "shazow": {
      "owner": "shazow",
      "lastExecuted": "2023-12-20T08:20:26.782Z"
    },
    "jinzhu": {
      "owner": "jinzhu",
      "lastExecuted": "2023-12-20T08:20:26.782Z"
    },
    "twpayne": {
      "owner": "twpayne",
      "lastExecuted": "2023-12-20T08:20:26.782Z"
    },
    "vilterp": {
      "owner": "vilterp",
      "lastExecuted": "2023-12-20T08:20:26.782Z"
    },
    "danielgatis": {
      "owner": "danielgatis",
      "lastExecuted": "2023-12-20T08:20:26.782Z"
    },
    "jamesturk": {
      "owner": "jamesturk",
      "lastExecuted": "2023-12-20T08:20:26.782Z"
    },
    "dpc": {
      "owner": "dpc",
      "lastExecuted": "2023-12-20T08:20:26.782Z"
    },
    "isaacs": {
      "owner": "isaacs",
      "lastExecuted": "2023-12-20T08:20:26.782Z"
    },
    "josevalim": {
      "owner": "josevalim",
      "lastExecuted": "2023-12-20T08:20:26.782Z"
    },
    "igrigorik": {
      "owner": "igrigorik",
      "lastExecuted": "2023-12-20T08:20:26.782Z"
    },
    "chrisdone": {
      "owner": "chrisdone",
      "lastExecuted": "2023-12-20T08:20:26.782Z"
    },
    "eferm": {
      "owner": "eferm",
      "lastExecuted": "2023-12-20T08:20:26.782Z"
    },
    "alexandru": {
      "owner": "alexandru",
      "lastExecuted": "2023-12-20T08:20:26.782Z"
    },
    "jbowes": {
      "owner": "jbowes",
      "lastExecuted": "2023-12-20T08:20:26.782Z"
    },
    "rauchg": {
      "owner": "rauchg",
      "lastExecuted": "2023-12-20T08:20:26.782Z"
    },
    "buger": {
      "owner": "buger",
      "lastExecuted": "2023-12-20T08:20:26.782Z"
    },
    "WIZARDISHUNGRY": {
      "owner": "WIZARDISHUNGRY",
      "lastExecuted": "2022-02-08T00:33:28.520Z"
    },
    "carlisia": {
      "owner": "carlisia",
      "lastExecuted": "2022-02-08T00:33:28.520Z"
    },
    "jlongster": {
      "owner": "jlongster",
      "lastExecuted": "2022-02-08T00:33:28.520Z"
    },
    "esden": {
      "owner": "esden",
      "lastExecuted": "2023-12-20T08:20:26.782Z"
    },
    "harperreed": {
      "owner": "harperreed",
      "lastExecuted": "2023-12-20T08:20:26.782Z"
    },
    "ai": {
      "owner": "ai",
      "lastExecuted": "2023-12-20T08:20:26.782Z"
    },
    "devongovett": {
      "owner": "devongovett",
      "lastExecuted": "2023-12-20T09:13:35.071Z"
    },
    "azu": {
      "owner": "azu",
      "lastExecuted": "2023-12-20T09:13:35.071Z"
    },
    "asciimoo": {
      "owner": "asciimoo",
      "lastExecuted": "2023-12-20T09:13:35.071Z"
    },
    "dottorblaster": {
      "owner": "dottorblaster",
      "lastExecuted": "2023-12-20T09:13:35.071Z"
    },
    "mame": {
      "owner": "mame",
      "lastExecuted": "2023-12-20T09:13:35.071Z"
    },
    "jherr": {
      "owner": "jherr",
      "lastExecuted": "2023-12-20T09:13:35.071Z"
    },
    "idan": {
      "owner": "idan",
      "lastExecuted": "2023-12-20T09:13:35.071Z"
    },
    "DmitryBaranovskiy": {
      "owner": "DmitryBaranovskiy",
      "lastExecuted": "2022-02-08T00:41:33.271Z"
    },
    "cmars": {
      "owner": "cmars",
      "lastExecuted": "2023-12-20T09:13:35.071Z"
    },
    "unixorn": {
      "owner": "unixorn",
      "lastExecuted": "2023-12-20T09:13:35.071Z"
    },
    "tj": {
      "owner": "tj",
      "lastExecuted": "2023-12-20T09:13:35.071Z"
    },
    "weierophinney": {
      "owner": "weierophinney",
      "lastExecuted": "2023-12-20T09:13:35.071Z"
    },
    "reconbot": {
      "owner": "reconbot",
      "lastExecuted": "2023-12-20T09:13:35.071Z"
    },
    "below": {
      "owner": "below",
      "lastExecuted": "2023-12-20T09:13:35.071Z"
    },
    "joelparkerhenderson": {
      "owner": "joelparkerhenderson",
      "lastExecuted": "2023-12-20T09:13:35.071Z"
    },
    "joebowbeer": {
      "owner": "joebowbeer",
      "lastExecuted": "2023-12-20T09:13:35.071Z"
    },
    "bvaughn": {
      "owner": "bvaughn",
      "lastExecuted": "2023-12-20T09:13:35.071Z"
    },
    "ytakano": {
      "owner": "ytakano",
      "lastExecuted": "2023-12-20T09:13:35.071Z"
    },
    "rafabene": {
      "owner": "rafabene",
      "lastExecuted": "2023-12-20T09:13:35.071Z"
    },
    "philnash": {
      "owner": "philnash",
      "lastExecuted": "2023-12-20T09:13:35.071Z"
    },
    "kant": {
      "owner": "kant",
      "lastExecuted": "2023-12-20T09:13:35.071Z"
    },
    "voxpelli": {
      "owner": "voxpelli",
      "lastExecuted": "2023-12-20T09:13:35.071Z"
    },
    "rapodaca": {
      "owner": "rapodaca",
      "lastExecuted": "2023-12-20T09:13:35.071Z"
    },
    "sgrove": {
      "owner": "sgrove",
      "lastExecuted": "2023-12-14T03:12:23.216Z"
    },
    "johnlindquist": {
      "owner": "johnlindquist",
      "lastExecuted": "2023-12-20T09:13:35.071Z"
    },
    "bpierre": {
      "owner": "bpierre",
      "lastExecuted": "2023-12-20T09:13:35.071Z"
    },
    "wraithgar": {
      "owner": "wraithgar",
      "lastExecuted": "2023-12-20T09:13:35.071Z"
    },
    "nzakas": {
      "owner": "nzakas",
      "lastExecuted": "2023-12-20T09:13:35.071Z"
    },
    "paulirish": {
      "owner": "paulirish",
      "lastExecuted": "2023-12-20T09:13:35.071Z"
    },
    "dominikh": {
      "owner": "dominikh",
      "lastExecuted": "2023-12-20T09:13:35.071Z"
    },
    "gr2m": {
      "owner": "gr2m",
      "lastExecuted": "2023-12-20T09:13:35.071Z"
    },
    "schappim": {
      "owner": "schappim",
      "lastExecuted": "2023-12-20T09:13:35.071Z"
    },
    "cloudhead": {
      "owner": "cloudhead",
      "lastExecuted": "2023-12-20T09:13:35.071Z"
    },
    "pudo": {
      "owner": "pudo",
      "lastExecuted": "2023-12-20T09:13:35.071Z"
    },
    "leeoniya": {
      "owner": "leeoniya",
      "lastExecuted": "2023-12-20T09:13:35.071Z"
    },
    "dparnell": {
      "owner": "dparnell",
      "lastExecuted": "2023-12-20T09:13:35.071Z"
    },
    "stefanv": {
      "owner": "stefanv",
      "lastExecuted": "2023-12-20T09:19:41.764Z"
    },
    "cbiffle": {
      "owner": "cbiffle",
      "lastExecuted": "2023-12-20T09:19:41.764Z"
    },
    "ljharb": {
      "owner": "ljharb",
      "lastExecuted": "2023-12-20T09:19:41.764Z"
    },
    "paulgb": {
      "owner": "paulgb",
      "lastExecuted": "2023-12-20T09:19:41.764Z"
    },
    "josephg": {
      "owner": "josephg",
      "lastExecuted": "2023-12-20T09:19:41.764Z"
    },
    "orta": {
      "owner": "orta",
      "lastExecuted": "2023-12-20T09:19:41.764Z"
    },
    "jart": {
      "owner": "jart",
      "lastExecuted": "2023-12-20T09:19:41.764Z"
    },
    "autonome": {
      "owner": "autonome",
      "lastExecuted": "2023-12-20T09:19:41.764Z"
    },
    "leebyron": {
      "owner": "leebyron",
      "lastExecuted": "2023-12-20T09:19:41.764Z"
    },
    "mcollina": {
      "owner": "mcollina",
      "lastExecuted": "2023-12-20T09:19:41.764Z"
    },
    "osterman": {
      "owner": "osterman",
      "lastExecuted": "2023-12-20T09:19:41.764Z"
    },
    "mscdex": {
      "owner": "mscdex",
      "lastExecuted": "2023-12-20T07:19:04.989Z"
    },
    "whitequark": {
      "owner": "whitequark",
      "lastExecuted": "2023-12-20T09:19:41.764Z"
    },
    "leandromoreira": {
      "owner": "leandromoreira",
      "lastExecuted": "2023-12-20T09:19:41.764Z"
    },
    "nat": {
      "owner": "nat",
      "lastExecuted": "2023-12-20T09:19:41.764Z"
    },
    "deanm": {
      "owner": "deanm",
      "lastExecuted": "2022-02-08T00:43:21.035Z"
    },
    "k1LoW": {
      "owner": "k1LoW",
      "lastExecuted": "2023-12-20T09:19:41.764Z"
    },
    "beaugunderson": {
      "owner": "beaugunderson",
      "lastExecuted": "2023-12-20T09:19:41.764Z"
    },
    "zander": {
      "owner": "zander",
      "lastExecuted": "2022-02-08T00:43:21.035Z"
    },
    "ahmedelgabri": {
      "owner": "ahmedelgabri",
      "lastExecuted": "2023-12-20T09:19:41.764Z"
    },
    "hooopo": {
      "owner": "hooopo",
      "lastExecuted": "2023-12-20T09:19:41.764Z"
    },
    "chriscoyier": {
      "owner": "chriscoyier",
      "lastExecuted": "2023-12-20T09:19:41.764Z"
    },
    "lrvick": {
      "owner": "lrvick",
      "lastExecuted": "2023-12-20T09:19:41.764Z"
    },
    "benfred": {
      "owner": "benfred",
      "lastExecuted": "2023-12-20T09:19:41.764Z"
    },
    "ashtom": {
      "owner": "ashtom",
      "lastExecuted": "2023-12-20T09:19:41.764Z"
    },
    "KyleAMathews": {
      "owner": "KyleAMathews",
      "lastExecuted": "2023-12-20T09:19:41.764Z"
    },
    "kornelski": {
      "owner": "kornelski",
      "lastExecuted": "2023-12-20T09:19:41.764Z"
    },
    "ordovician": {
      "owner": "ordovician",
      "lastExecuted": "2022-02-08T00:43:21.035Z"
    },
    "geohot": {
      "owner": "geohot",
      "lastExecuted": "2022-02-08T00:43:21.035Z"
    },
    "ben-xo": {
      "owner": "ben-xo",
      "lastExecuted": "2023-12-20T09:19:41.764Z"
    },
    "pes10k": {
      "owner": "pes10k",
      "lastExecuted": "2023-12-20T09:19:41.764Z"
    },
    "ralphschindler": {
      "owner": "ralphschindler",
      "lastExecuted": "2023-12-20T07:19:04.989Z"
    },
    "StoneCypher": {
      "owner": "StoneCypher",
      "lastExecuted": "2023-12-20T07:19:04.989Z"
    },
    "nathanhoad": {
      "owner": "nathanhoad",
      "lastExecuted": "2023-12-20T07:19:04.989Z"
    },
    "vpj": {
      "owner": "vpj",
      "lastExecuted": "2023-12-20T07:19:04.989Z"
    },
    "mathiasbynens": {
      "owner": "mathiasbynens",
      "lastExecuted": "2023-12-20T07:19:04.989Z"
    },
    "cheshire137": {
      "owner": "cheshire137",
      "lastExecuted": "2023-12-20T07:19:04.989Z"
    },
    "foosel": {
      "owner": "foosel",
      "lastExecuted": "2023-12-20T07:19:04.989Z"
    },
    "mvayngrib": {
      "owner": "mvayngrib",
      "lastExecuted": "2023-12-20T07:19:04.989Z"
    },
    "preslavrachev": {
      "owner": "preslavrachev",
      "lastExecuted": "2023-12-20T07:19:04.989Z"
    },
    "joelhooks": {
      "owner": "joelhooks",
      "lastExecuted": "2023-12-20T07:19:04.989Z"
    },
    "evilsocket": {
      "owner": "evilsocket",
      "lastExecuted": "2023-12-20T07:19:04.989Z"
    },
    "kuchin": {
      "owner": "kuchin",
      "lastExecuted": "2023-12-20T07:19:04.989Z"
    },
    "fgnass": {
      "owner": "fgnass",
      "lastExecuted": "2023-12-20T07:19:04.989Z"
    },
    "staltz": {
      "owner": "staltz",
      "lastExecuted": "2023-12-20T07:19:04.989Z"
    },
    "utx0": {
      "owner": "utx0",
      "lastExecuted": "2022-02-08T00:43:21.035Z"
    },
    "ska80": {
      "owner": "ska80",
      "lastExecuted": "2023-12-20T07:19:04.989Z"
    },
    "mjackson": {
      "owner": "mjackson",
      "lastExecuted": "2023-12-20T07:19:04.989Z"
    },
    "jakearchibald": {
      "owner": "jakearchibald",
      "lastExecuted": "2023-12-20T07:19:04.989Z"
    },
    "sorin-ionescu": {
      "owner": "sorin-ionescu",
      "lastExecuted": "2022-02-08T00:43:21.035Z"
    },
    "sparanoid": {
      "owner": "sparanoid",
      "lastExecuted": "2023-12-20T07:19:04.989Z"
    },
    "brandur": {
      "owner": "brandur",
      "lastExecuted": "2023-12-20T07:19:04.989Z"
    },
    "mrdoob": {
      "owner": "mrdoob",
      "lastExecuted": "2023-12-20T07:19:04.989Z"
    },
    "aaronbassett": {
      "owner": "aaronbassett",
      "lastExecuted": "2023-12-20T07:19:04.989Z"
    },
    "mdo": {
      "owner": "mdo",
      "lastExecuted": "2023-12-20T07:19:04.989Z"
    },
    "matryer": {
      "owner": "matryer",
      "lastExecuted": "2023-12-20T07:19:04.989Z"
    },
    "badsyntax": {
      "owner": "badsyntax",
      "lastExecuted": "2023-12-20T07:19:04.989Z"
    },
    "radames": {
      "owner": "radames",
      "lastExecuted": "2023-12-20T07:19:04.989Z"
    },
    "schmidsi": {
      "owner": "schmidsi",
      "lastExecuted": "2023-12-20T07:19:04.989Z"
    },
    "mirisuzanne": {
      "owner": "mirisuzanne",
      "lastExecuted": "2023-12-20T07:19:04.989Z"
    },
    "developit": {
      "owner": "developit",
      "lastExecuted": "2023-12-20T07:19:04.989Z"
    },
    "lucidrains": {
      "owner": "lucidrains",
      "lastExecuted": "2023-12-20T07:19:04.989Z"
    },
    "addyosmani": {
      "owner": "addyosmani",
      "lastExecuted": "2023-12-20T07:19:04.989Z"
    },
    "schmichael": {
      "owner": "schmichael",
      "lastExecuted": "2023-12-20T07:43:50.101Z"
    },
    "peterbourgon": {
      "owner": "peterbourgon",
      "lastExecuted": "2023-12-20T07:43:50.101Z"
    },
    "posabsolute": {
      "owner": "posabsolute",
      "lastExecuted": "2023-12-20T07:43:50.101Z"
    },
    "blakebyrnes": {
      "owner": "blakebyrnes",
      "lastExecuted": "2023-12-20T07:43:50.101Z"
    },
    "lostintangent": {
      "owner": "lostintangent",
      "lastExecuted": "2023-12-09T23:41:03.488Z"
    },
    "ryoqun": {
      "owner": "ryoqun",
      "lastExecuted": "2023-12-20T07:43:50.101Z"
    },
    "keithamus": {
      "owner": "keithamus",
      "lastExecuted": "2023-12-20T07:43:50.101Z"
    },
    "damieng": {
      "owner": "damieng",
      "lastExecuted": "2023-12-20T07:43:50.101Z"
    },
    "leereilly": {
      "owner": "leereilly",
      "lastExecuted": "2023-12-20T07:43:50.101Z"
    },
    "ianwalter": {
      "owner": "ianwalter",
      "lastExecuted": "2023-12-20T07:43:50.101Z"
    },
    "medikoo": {
      "owner": "medikoo",
      "lastExecuted": "2023-12-20T07:43:50.101Z"
    },
    "pcardune": {
      "owner": "pcardune",
      "lastExecuted": "2023-12-20T07:43:50.101Z"
    },
    "orther": {
      "owner": "orther",
      "lastExecuted": "2022-02-08T00:46:14.072Z"
    },
    "domenkozar": {
      "owner": "domenkozar",
      "lastExecuted": "2023-12-20T07:43:50.101Z"
    },
    "travi": {
      "owner": "travi",
      "lastExecuted": "2023-12-20T07:43:50.101Z"
    },
    "gz": {
      "owner": "gz",
      "lastExecuted": "2023-12-20T07:43:50.101Z"
    },
    "daurnimator": {
      "owner": "daurnimator",
      "lastExecuted": "2023-12-20T07:43:50.101Z"
    },
    "xvaara": {
      "owner": "xvaara",
      "lastExecuted": "2023-12-20T07:43:50.101Z"
    },
    "glowcoil": {
      "owner": "glowcoil",
      "lastExecuted": "2023-12-20T07:43:50.101Z"
    },
    "csuwildcat": {
      "owner": "csuwildcat",
      "lastExecuted": "2023-12-20T07:43:50.101Z"
    },
    "tarao": {
      "owner": "tarao",
      "lastExecuted": "2023-12-20T07:43:50.101Z"
    },
    "ndeloof": {
      "owner": "ndeloof",
      "lastExecuted": "2023-12-20T07:43:50.101Z"
    },
    "antonmedv": {
      "owner": "antonmedv",
      "lastExecuted": "2023-12-20T07:43:50.101Z"
    },
    "jwilk": {
      "owner": "jwilk",
      "lastExecuted": "2022-02-08T00:46:14.072Z"
    },
    "joesepi": {
      "owner": "joesepi",
      "lastExecuted": "2023-12-20T07:43:50.101Z"
    },
    "marijnh": {
      "owner": "marijnh",
      "lastExecuted": "2023-12-20T07:43:50.101Z"
    },
    "kittinan": {
      "owner": "kittinan",
      "lastExecuted": "2023-12-20T07:43:50.101Z"
    },
    "argp": {
      "owner": "argp",
      "lastExecuted": "2022-02-08T00:46:14.072Z"
    },
    "yegle": {
      "owner": "yegle",
      "lastExecuted": "2023-12-20T07:43:50.101Z"
    },
    "muesli": {
      "owner": "muesli",
      "lastExecuted": "2023-12-20T07:43:50.101Z"
    },
    "macmade": {
      "owner": "macmade",
      "lastExecuted": "2023-12-20T07:43:50.101Z"
    },
    "esatterwhite": {
      "owner": "esatterwhite",
      "lastExecuted": "2023-12-20T08:03:05.367Z"
    },
    "jlfwong": {
      "owner": "jlfwong",
      "lastExecuted": "2023-12-20T08:03:05.367Z"
    },
    "stemount": {
      "owner": "stemount",
      "lastExecuted": "2022-02-08T00:46:14.072Z"
    },
    "alanshaw": {
      "owner": "alanshaw",
      "lastExecuted": "2023-12-20T08:03:05.367Z"
    },
    "justinethier": {
      "owner": "justinethier",
      "lastExecuted": "2023-12-20T08:03:05.367Z"
    },
    "TristanCacqueray": {
      "owner": "TristanCacqueray",
      "lastExecuted": "2023-12-20T08:03:05.367Z"
    },
    "adamschwartz": {
      "owner": "adamschwartz",
      "lastExecuted": "2023-12-20T08:03:05.367Z"
    },
    "caspervonb": {
      "owner": "caspervonb",
      "lastExecuted": "2023-12-20T08:03:05.367Z"
    },
    "florinutz": {
      "owner": "florinutz",
      "lastExecuted": "2023-12-20T08:03:05.367Z"
    },
    "ahmetb": {
      "owner": "ahmetb",
      "lastExecuted": "2023-12-20T08:03:05.367Z"
    },
    "sorenisanerd": {
      "owner": "sorenisanerd",
      "lastExecuted": "2023-12-20T08:03:05.367Z"
    },
    "creiser": {
      "owner": "creiser",
      "lastExecuted": "2023-12-20T08:03:05.367Z"
    },
    "dvschultz": {
      "owner": "dvschultz",
      "lastExecuted": "2023-12-13T03:24:48.616Z"
    },
    "imdario": {
      "owner": "imdario",
      "lastExecuted": "2022-02-08T00:48:18.635Z"
    },
    "jlengstorf": {
      "owner": "jlengstorf",
      "lastExecuted": "2023-12-20T08:03:05.367Z"
    },
    "widmogrod": {
      "owner": "widmogrod",
      "lastExecuted": "2023-12-20T08:03:05.367Z"
    },
    "miguelmota": {
      "owner": "miguelmota",
      "lastExecuted": "2023-12-20T08:03:05.367Z"
    },
    "sindresorhus": {
      "owner": "sindresorhus",
      "lastExecuted": "2023-12-20T08:03:05.367Z"
    },
    "ichiriac": {
      "owner": "ichiriac",
      "lastExecuted": "2023-12-20T08:03:05.367Z"
    },
    "zakjan": {
      "owner": "zakjan",
      "lastExecuted": "2023-12-20T08:03:05.367Z"
    },
    "mpolden": {
      "owner": "mpolden",
      "lastExecuted": "2023-12-20T08:51:32.151Z"
    },
    "knpwrs": {
      "owner": "knpwrs",
      "lastExecuted": "2023-12-20T08:51:32.151Z"
    },
    "LeaVerou": {
      "owner": "LeaVerou",
      "lastExecuted": "2023-12-20T08:51:32.151Z"
    },
    "jonhoo": {
      "owner": "jonhoo",
      "lastExecuted": "2023-12-20T08:51:32.151Z"
    },
    "ttsiodras": {
      "owner": "ttsiodras",
      "lastExecuted": "2023-12-20T08:51:32.151Z"
    },
    "daminetreg": {
      "owner": "daminetreg",
      "lastExecuted": "2023-12-20T08:51:32.151Z"
    },
    "twostraws": {
      "owner": "twostraws",
      "lastExecuted": "2023-12-20T08:51:32.151Z"
    },
    "runemadsen": {
      "owner": "runemadsen",
      "lastExecuted": "2023-12-20T08:51:32.151Z"
    },
    "dtinth": {
      "owner": "dtinth",
      "lastExecuted": "2023-12-20T08:51:32.151Z"
    },
    "bcoe": {
      "owner": "bcoe",
      "lastExecuted": "2023-12-20T08:51:32.151Z"
    },
    "kontrafiktion": {
      "owner": "kontrafiktion",
      "lastExecuted": "2023-12-20T08:51:32.151Z"
    },
    "fangpenlin": {
      "owner": "fangpenlin",
      "lastExecuted": "2023-12-20T08:51:32.151Z"
    },
    "dschwen": {
      "owner": "dschwen",
      "lastExecuted": "2023-12-20T08:51:32.151Z"
    },
    "jheer": {
      "owner": "jheer",
      "lastExecuted": "2023-12-20T08:51:32.151Z"
    },
    "danburzo": {
      "owner": "danburzo",
      "lastExecuted": "2023-12-20T08:51:32.151Z"
    },
    "amarnus": {
      "owner": "amarnus",
      "lastExecuted": "2023-12-20T08:51:32.151Z"
    },
    "daylerees": {
      "owner": "daylerees",
      "lastExecuted": "2022-02-08T00:48:18.635Z"
    },
    "ptigas": {
      "owner": "ptigas",
      "lastExecuted": "2023-12-20T08:51:32.151Z"
    },
    "MaximRouiller": {
      "owner": "MaximRouiller",
      "lastExecuted": "2023-12-20T08:51:32.151Z"
    },
    "MichMich": {
      "owner": "MichMich",
      "lastExecuted": "2023-12-20T08:51:32.151Z"
    },
    "alangpierce": {
      "owner": "alangpierce",
      "lastExecuted": "2022-02-08T00:48:18.635Z"
    },
    "ahaywood": {
      "owner": "ahaywood",
      "lastExecuted": "2023-12-20T10:04:22.547Z"
    },
    "ruyadorno": {
      "owner": "ruyadorno",
      "lastExecuted": "2023-12-20T10:04:22.547Z"
    },
    "melonamin": {
      "owner": "melonamin",
      "lastExecuted": "2023-12-20T10:04:22.547Z"
    },
    "anvaka": {
      "owner": "anvaka",
      "lastExecuted": "2023-12-20T10:04:22.547Z"
    },
    "clone1018": {
      "owner": "clone1018",
      "lastExecuted": "2023-12-20T10:04:22.547Z"
    },
    "Ch00k": {
      "owner": "Ch00k",
      "lastExecuted": "2023-12-20T10:04:22.547Z"
    },
    "april": {
      "owner": "april",
      "lastExecuted": "2023-12-20T10:04:22.547Z"
    },
    "mikolalysenko": {
      "owner": "mikolalysenko",
      "lastExecuted": "2023-12-12T03:18:30.506Z"
    },
    "spences10": {
      "owner": "spences10",
      "lastExecuted": "2023-12-20T10:04:22.547Z"
    },
    "rachelnabors": {
      "owner": "rachelnabors",
      "lastExecuted": "2023-12-20T10:04:22.547Z"
    },
    "manateelazycat": {
      "owner": "manateelazycat",
      "lastExecuted": "2023-12-20T10:04:22.547Z"
    },
    "tsandall": {
      "owner": "tsandall",
      "lastExecuted": "2023-12-20T10:04:22.547Z"
    },
    "jiriknesl": {
      "owner": "jiriknesl",
      "lastExecuted": "2023-12-20T10:04:22.547Z"
    },
    "tugstugi": {
      "owner": "tugstugi",
      "lastExecuted": "2023-12-20T10:04:22.547Z"
    },
    "fancycode": {
      "owner": "fancycode",
      "lastExecuted": "2023-12-20T10:04:22.547Z"
    },
    "cherscarlett": {
      "owner": "cherscarlett",
      "lastExecuted": "2023-12-20T10:21:23.881Z"
    },
    "gregberge": {
      "owner": "gregberge",
      "lastExecuted": "2023-12-20T10:04:22.547Z"
    },
    "padenot": {
      "owner": "padenot",
      "lastExecuted": "2023-12-20T10:04:22.547Z"
    },
    "Firstyear": {
      "owner": "Firstyear",
      "lastExecuted": "2023-12-20T10:04:22.547Z"
    },
    "mshick": {
      "owner": "mshick",
      "lastExecuted": "2023-12-20T10:04:22.547Z"
    },
    "nicks": {
      "owner": "nicks",
      "lastExecuted": "2023-12-20T10:04:22.547Z"
    },
    "terlar": {
      "owner": "terlar",
      "lastExecuted": "2023-12-20T10:04:22.547Z"
    },
    "vjpr": {
      "owner": "vjpr",
      "lastExecuted": "2023-12-20T10:21:23.881Z"
    },
    "siedentop": {
      "owner": "siedentop",
      "lastExecuted": "2023-12-20T10:21:23.881Z"
    },
    "tonsky": {
      "owner": "tonsky",
      "lastExecuted": "2023-12-20T10:21:23.881Z"
    },
    "peacekeeper": {
      "owner": "peacekeeper",
      "lastExecuted": "2023-12-20T10:21:23.881Z"
    },
    "jerdog": {
      "owner": "jerdog",
      "lastExecuted": "2023-12-20T10:21:23.881Z"
    },
    "trusktr": {
      "owner": "trusktr",
      "lastExecuted": "2023-12-20T10:21:23.881Z"
    },
    "wilsonmar": {
      "owner": "wilsonmar",
      "lastExecuted": "2023-12-20T10:21:23.881Z"
    },
    "typhonrt": {
      "owner": "typhonrt",
      "lastExecuted": "2023-12-20T10:21:23.881Z"
    },
    "travisbrown": {
      "owner": "travisbrown",
      "lastExecuted": "2023-12-20T10:21:23.881Z"
    },
    "lirantal": {
      "owner": "lirantal",
      "lastExecuted": "2023-12-20T10:21:23.881Z"
    },
    "andygrunwald": {
      "owner": "andygrunwald",
      "lastExecuted": "2023-12-20T10:21:23.881Z"
    },
    "ekzhu": {
      "owner": "ekzhu",
      "lastExecuted": "2023-12-20T10:21:23.881Z"
    },
    "dbanksdesign": {
      "owner": "dbanksdesign",
      "lastExecuted": "2023-12-20T10:27:42.860Z"
    },
    "philipwalton": {
      "owner": "philipwalton",
      "lastExecuted": "2023-12-20T10:27:42.860Z"
    },
    "colemickens": {
      "owner": "colemickens",
      "lastExecuted": "2023-12-20T10:27:42.860Z"
    },
    "rougier": {
      "owner": "rougier",
      "lastExecuted": "2023-12-20T10:27:42.860Z"
    },
    "newpavlov": {
      "owner": "newpavlov",
      "lastExecuted": "2023-12-20T10:27:42.860Z"
    },
    "RalfJung": {
      "owner": "RalfJung",
      "lastExecuted": "2023-12-20T10:27:42.860Z"
    },
    "deluan": {
      "owner": "deluan",
      "lastExecuted": "2023-12-20T10:27:42.860Z"
    },
    "keijiro": {
      "owner": "keijiro",
      "lastExecuted": "2023-12-20T10:27:42.860Z"
    },
    "allenap": {
      "owner": "allenap",
      "lastExecuted": "2023-12-20T08:33:05.275Z"
    },
    "jwalter": {
      "owner": "jwalter",
      "lastExecuted": "2023-12-20T08:33:05.275Z"
    },
    "pahen": {
      "owner": "pahen",
      "lastExecuted": "2022-02-08T00:57:18.839Z"
    },
    "agrinman": {
      "owner": "agrinman",
      "lastExecuted": "2023-12-20T08:33:05.275Z"
    },
    "danieltott": {
      "owner": "danieltott",
      "lastExecuted": "2023-12-20T08:33:05.275Z"
    },
    "ilg-ul": {
      "owner": "ilg-ul",
      "lastExecuted": "2023-12-20T08:33:05.275Z"
    },
    "svenefftinge": {
      "owner": "svenefftinge",
      "lastExecuted": "2023-12-20T08:33:05.275Z"
    },
    "ulyssessouza": {
      "owner": "ulyssessouza",
      "lastExecuted": "2023-12-20T08:33:05.275Z"
    },
    "weskerfoot": {
      "owner": "weskerfoot",
      "lastExecuted": "2023-12-20T08:33:05.275Z"
    },
    "spantaleev": {
      "owner": "spantaleev",
      "lastExecuted": "2023-12-20T08:33:05.275Z"
    },
    "dcoxall": {
      "owner": "dcoxall",
      "lastExecuted": "2023-12-20T10:27:42.860Z"
    },
    "palmskog": {
      "owner": "palmskog",
      "lastExecuted": "2023-12-20T10:27:42.860Z"
    },
    "unixpickle": {
      "owner": "unixpickle",
      "lastExecuted": "2023-12-20T10:27:42.860Z"
    },
    "evanw": {
      "owner": "evanw",
      "lastExecuted": "2023-12-20T10:27:42.860Z"
    },
    "robotlolita": {
      "owner": "robotlolita",
      "lastExecuted": "2023-12-20T08:33:05.275Z"
    },
    "Bren2010": {
      "owner": "Bren2010",
      "lastExecuted": "2023-12-20T09:05:31.107Z"
    },
    "riebschlager": {
      "owner": "riebschlager",
      "lastExecuted": "2023-12-20T09:05:31.107Z"
    },
    "nfultz": {
      "owner": "nfultz",
      "lastExecuted": "2023-12-20T09:05:31.107Z"
    },
    "mli": {
      "owner": "mli",
      "lastExecuted": "2022-02-08T00:57:18.839Z"
    },
    "nlf": {
      "owner": "nlf",
      "lastExecuted": "2023-12-20T09:05:31.107Z"
    },
    "tmk": {
      "owner": "tmk",
      "lastExecuted": "2023-12-20T09:05:31.107Z"
    },
    "spalladino": {
      "owner": "spalladino",
      "lastExecuted": "2023-12-20T09:05:31.107Z"
    },
    "danbev": {
      "owner": "danbev",
      "lastExecuted": "2023-12-20T09:05:31.107Z"
    },
    "iansu": {
      "owner": "iansu",
      "lastExecuted": "2023-12-20T09:05:31.107Z"
    },
    "Xaymar": {
      "owner": "Xaymar",
      "lastExecuted": "2022-02-08T00:57:18.839Z"
    },
    "gitawego": {
      "owner": "gitawego",
      "lastExecuted": "2023-12-20T09:05:31.107Z"
    },
    "jasnell": {
      "owner": "jasnell",
      "lastExecuted": "2023-12-20T09:25:51.311Z"
    },
    "mischah": {
      "owner": "mischah",
      "lastExecuted": "2023-12-20T09:25:51.311Z"
    },
    "mdnmdn": {
      "owner": "mdnmdn",
      "lastExecuted": "2023-12-20T09:25:51.311Z"
    },
    "theicfire": {
      "owner": "theicfire",
      "lastExecuted": "2023-12-20T09:25:51.311Z"
    },
    "ptkdev": {
      "owner": "ptkdev",
      "lastExecuted": "2023-12-20T09:25:51.311Z"
    },
    "xpepper": {
      "owner": "xpepper",
      "lastExecuted": "2023-12-20T09:25:51.311Z"
    },
    "jazzdan": {
      "owner": "jazzdan",
      "lastExecuted": "2023-12-20T09:25:51.311Z"
    },
    "refset": {
      "owner": "refset",
      "lastExecuted": "2023-12-20T09:25:51.311Z"
    },
    "nikoheikkila": {
      "owner": "nikoheikkila",
      "lastExecuted": "2023-12-20T09:25:51.311Z"
    },
    "philipp-spiess": {
      "owner": "philipp-spiess",
      "lastExecuted": "2023-12-20T09:25:51.311Z"
    },
    "thanpolas": {
      "owner": "thanpolas",
      "lastExecuted": "2023-12-20T09:32:06.582Z"
    },
    "KATT": {
      "owner": "KATT",
      "lastExecuted": "2023-12-20T09:32:06.582Z"
    },
    "darcyclarke": {
      "owner": "darcyclarke",
      "lastExecuted": "2023-12-20T09:32:06.582Z"
    },
    "bennycode": {
      "owner": "bennycode",
      "lastExecuted": "2023-12-20T09:32:06.582Z"
    },
    "ofhouse": {
      "owner": "ofhouse",
      "lastExecuted": "2023-12-20T09:32:06.582Z"
    },
    "rhyspowell": {
      "owner": "rhyspowell",
      "lastExecuted": "2023-12-20T09:32:06.582Z"
    },
    "dwwoelfel": {
      "owner": "dwwoelfel",
      "lastExecuted": "2022-02-08T01:27:24.738Z"
    },
    "reuben": {
      "owner": "reuben",
      "lastExecuted": "2023-12-20T09:32:06.582Z"
    },
    "raae": {
      "owner": "raae",
      "lastExecuted": "2023-12-20T09:32:06.582Z"
    },
    "lambdageek": {
      "owner": "lambdageek",
      "lastExecuted": "2023-12-20T09:32:06.582Z"
    },
    "geerlingguy": {
      "owner": "geerlingguy",
      "lastExecuted": "2023-12-20T09:38:21.698Z"
    },
    "justincormack": {
      "owner": "justincormack",
      "lastExecuted": "2023-12-20T09:38:21.698Z"
    },
    "hackergrrl": {
      "owner": "hackergrrl",
      "lastExecuted": "2023-12-20T09:38:21.698Z"
    },
    "jkup": {
      "owner": "jkup",
      "lastExecuted": "2023-12-20T09:38:21.698Z"
    },
    "MylesBorins": {
      "owner": "MylesBorins",
      "lastExecuted": "2023-12-20T09:38:21.698Z"
    },
    "electerious": {
      "owner": "electerious",
      "lastExecuted": "2023-12-20T09:38:21.698Z"
    },
    "bnb": {
      "owner": "bnb",
      "lastExecuted": "2023-12-20T09:38:21.698Z"
    },
    "uhafner": {
      "owner": "uhafner",
      "lastExecuted": "2023-12-20T09:38:21.698Z"
    },
    "hlissner": {
      "owner": "hlissner",
      "lastExecuted": "2023-12-20T09:44:31.224Z"
    },
    "moxie0": {
      "owner": "moxie0",
      "lastExecuted": "2022-02-08T01:27:24.738Z"
    },
    "fogleman": {
      "owner": "fogleman",
      "lastExecuted": "2023-12-20T09:44:31.224Z"
    },
    "hadim": {
      "owner": "hadim",
      "lastExecuted": "2023-12-20T09:44:31.224Z"
    },
    "igorsantos07": {
      "owner": "igorsantos07",
      "lastExecuted": "2023-12-20T09:44:31.224Z"
    },
    "kotakanbe": {
      "owner": "kotakanbe",
      "lastExecuted": "2023-12-20T09:44:31.224Z"
    },
    "christianbundy": {
      "owner": "christianbundy",
      "lastExecuted": "2023-12-20T09:44:31.224Z"
    },
    "amanda-mitchell": {
      "owner": "amanda-mitchell",
      "lastExecuted": "2023-12-20T09:50:43.070Z"
    },
    "banga": {
      "owner": "banga",
      "lastExecuted": "2023-12-20T09:50:43.070Z"
    },
    "leolabs": {
      "owner": "leolabs",
      "lastExecuted": "2023-12-20T09:50:43.070Z"
    },
    "kostko": {
      "owner": "kostko",
      "lastExecuted": "2023-12-20T09:50:43.070Z"
    },
    "DenisCarriere": {
      "owner": "DenisCarriere",
      "lastExecuted": "2023-12-20T09:50:43.070Z"
    },
    "ChristopherBiscardi": {
      "owner": "ChristopherBiscardi",
      "lastExecuted": "2023-12-20T09:50:43.070Z"
    },
    "poljar": {
      "owner": "poljar",
      "lastExecuted": "2023-12-20T09:50:43.070Z"
    },
    "transitive-bullshit": {
      "owner": "transitive-bullshit",
      "lastExecuted": "2023-12-20T09:57:04.019Z"
    },
    "BinRoot": {
      "owner": "BinRoot",
      "lastExecuted": "2023-12-20T09:57:04.019Z"
    },
    "obmarg": {
      "owner": "obmarg",
      "lastExecuted": "2023-12-20T09:57:04.019Z"
    },
    "impressivewebs": {
      "owner": "impressivewebs",
      "lastExecuted": "2022-02-08T01:50:30.160Z"
    },
    "ret2libc": {
      "owner": "ret2libc",
      "lastExecuted": "2023-12-20T09:57:04.019Z"
    },
    "juanfranblanco": {
      "owner": "juanfranblanco",
      "lastExecuted": "2023-12-20T09:57:04.019Z"
    },
    "paulmillr": {
      "owner": "paulmillr",
      "lastExecuted": "2023-12-20T10:12:51.175Z"
    },
    "racerxdl": {
      "owner": "racerxdl",
      "lastExecuted": "2023-12-20T10:12:51.175Z"
    },
    "benedfit": {
      "owner": "benedfit",
      "lastExecuted": "2023-12-20T10:12:51.175Z"
    },
    "kelindar": {
      "owner": "kelindar",
      "lastExecuted": "2023-12-20T10:12:51.175Z"
    },
    "gorhill": {
      "owner": "gorhill",
      "lastExecuted": "2023-12-20T10:12:51.175Z"
    },
    "dte": {
      "owner": "dte",
      "lastExecuted": "2023-12-20T10:12:51.175Z"
    },
    "leafac": {
      "owner": "leafac",
      "lastExecuted": "2023-12-20T10:12:51.175Z"
    },
    "amasad": {
      "owner": "amasad",
      "lastExecuted": "2022-02-08T01:50:30.160Z"
    },
    "hzoo": {
      "owner": "hzoo",
      "lastExecuted": "2023-12-20T10:33:52.375Z"
    },
    "ccojocar": {
      "owner": "ccojocar",
      "lastExecuted": "2023-12-20T10:33:52.375Z"
    },
    "jtpio": {
      "owner": "jtpio",
      "lastExecuted": "2023-12-20T10:33:52.375Z"
    },
    "merryt": {
      "owner": "merryt",
      "lastExecuted": "2023-12-20T10:33:52.375Z"
    },
    "cookiengineer": {
      "owner": "cookiengineer",
      "lastExecuted": "2023-12-20T10:33:52.375Z"
    },
    "VeNoMouS": {
      "owner": "VeNoMouS",
      "lastExecuted": "2023-12-20T10:39:56.801Z"
    },
    "guybedford": {
      "owner": "guybedford",
      "lastExecuted": "2023-12-20T10:39:56.801Z"
    },
    "justinpinkney": {
      "owner": "justinpinkney",
      "lastExecuted": "2023-12-20T10:39:56.801Z"
    },
    "boyter": {
      "owner": "boyter",
      "lastExecuted": "2023-12-20T10:46:19.916Z"
    },
    "Canop": {
      "owner": "Canop",
      "lastExecuted": "2023-12-20T10:46:19.916Z"
    },
    "adriancooney": {
      "owner": "adriancooney",
      "lastExecuted": "2023-12-20T10:46:19.916Z"
    },
    "eddiejaoude": {
      "owner": "eddiejaoude",
      "lastExecuted": "2023-12-20T10:46:19.916Z"
    },
    "seba-1511": {
      "owner": "seba-1511",
      "lastExecuted": "2022-02-08T02:08:46.620Z"
    },
    "sidkshatriya": {
      "owner": "sidkshatriya",
      "lastExecuted": "2023-12-20T07:25:15.410Z"
    },
    "badu": {
      "owner": "badu",
      "lastExecuted": "2023-12-20T07:25:15.410Z"
    },
    "daira": {
      "owner": "daira",
      "lastExecuted": "2023-12-19T22:58:20.552Z"
    },
    "erikgrinaker": {
      "owner": "erikgrinaker",
      "lastExecuted": "2023-12-20T07:25:15.410Z"
    },
    "rogeralsing": {
      "owner": "rogeralsing",
      "lastExecuted": "2023-12-20T07:31:29.564Z"
    },
    "phumpal": {
      "owner": "phumpal",
      "lastExecuted": "2023-12-20T07:31:29.564Z"
    },
    "tekezo": {
      "owner": "tekezo",
      "lastExecuted": "2023-12-20T07:31:29.564Z"
    },
    "lgaticaq": {
      "owner": "lgaticaq",
      "lastExecuted": "2023-12-20T07:37:41.031Z"
    },
    "posva": {
      "owner": "posva",
      "lastExecuted": "2023-12-20T07:37:41.031Z"
    },
    "creafz": {
      "owner": "creafz",
      "lastExecuted": "2023-12-20T07:37:41.031Z"
    },
    "tabatkins": {
      "owner": "tabatkins",
      "lastExecuted": "2023-12-20T07:50:00.105Z"
    },
    "nirev": {
      "owner": "nirev",
      "lastExecuted": "2023-12-20T07:50:00.105Z"
    },
    "medvednikov": {
      "owner": "medvednikov",
      "lastExecuted": "2023-12-20T07:56:08.149Z"
    },
    "dvcrn": {
      "owner": "dvcrn",
      "lastExecuted": "2023-12-20T07:56:08.149Z"
    },
    "vadimdemedes": {
      "owner": "vadimdemedes",
      "lastExecuted": "2023-12-20T08:11:51.252Z"
    },
    "landakram": {
      "owner": "landakram",
      "lastExecuted": "2023-12-20T08:11:51.252Z"
    },
    "junegunn": {
      "owner": "junegunn",
      "lastExecuted": "2023-12-20T08:11:51.252Z"
    },
    "ldionne": {
      "owner": "ldionne",
      "lastExecuted": "2023-12-20T08:26:43.525Z"
    },
    "shime": {
      "owner": "shime",
      "lastExecuted": "2023-12-20T08:26:43.525Z"
    },
    "cgreening": {
      "owner": "cgreening",
      "lastExecuted": "2023-12-20T08:39:04.861Z"
    },
    "bamos": {
      "owner": "bamos",
      "lastExecuted": "2023-12-20T08:39:04.861Z"
    },
    "frauzufall": {
      "owner": "frauzufall",
      "lastExecuted": "2023-12-20T08:45:21.444Z"
    },
    "Jarred-Sumner": {
      "owner": "Jarred-Sumner",
      "lastExecuted": "2023-12-20T08:45:21.444Z"
    },
    "brikis98": {
      "owner": "brikis98",
      "lastExecuted": "2023-12-09T19:55:29.233Z"
    },
    "borisdayma": {
      "owner": "borisdayma",
      "lastExecuted": "2023-12-20T08:57:47.622Z"
    },
    "thassiov": {
      "owner": "thassiov",
      "lastExecuted": "2023-12-19T21:44:49.619Z"
    },
    "oleavr": {
      "owner": "oleavr",
      "lastExecuted": "2023-12-19T23:32:55.103Z"
    },
    "ndimatteo": {
      "owner": "ndimatteo",
      "lastExecuted": "2023-12-19T23:32:55.103Z"
    },
    "piotrwitek": {
      "owner": "piotrwitek",
      "lastExecuted": "2023-12-19T19:58:05.105Z"
    },
    "rnystrom": {
      "owner": "rnystrom",
      "lastExecuted": "2023-12-19T19:58:05.105Z"
    },
    "dvc94ch": {
      "owner": "dvc94ch",
      "lastExecuted": "2023-12-09T20:38:11.993Z"
    },
    "joelnet": {
      "owner": "joelnet",
      "lastExecuted": "2022-02-08T02:21:41.691Z"
    },
    "aatxe": {
      "owner": "aatxe",
      "lastExecuted": "2023-12-09T21:37:30.039Z"
    },
    "saljam": {
      "owner": "saljam",
      "lastExecuted": "2023-12-09T19:43:21.922Z"
    },
    "h00die": {
      "owner": "h00die",
      "lastExecuted": "2023-12-09T19:43:21.922Z"
    },
    "Unitech": {
      "owner": "Unitech",
      "lastExecuted": "2023-12-09T19:43:21.922Z"
    },
    "tals": {
      "owner": "tals",
      "lastExecuted": "2023-12-09T20:02:08.662Z"
    },
    "nrc": {
      "owner": "nrc",
      "lastExecuted": "2023-12-09T20:02:08.662Z"
    },
    "Ovilia": {
      "owner": "Ovilia",
      "lastExecuted": "2023-12-09T20:50:33.110Z"
    },
    "achiku": {
      "owner": "achiku",
      "lastExecuted": "2023-12-09T20:50:33.110Z"
    },
    "m-ou-se": {
      "owner": "m-ou-se",
      "lastExecuted": "2023-12-09T21:37:30.039Z"
    },
    "elrumordelaluz": {
      "owner": "elrumordelaluz",
      "lastExecuted": "2023-12-09T21:37:30.039Z"
    },
    "wighawag": {
      "owner": "wighawag",
      "lastExecuted": "2023-12-09T21:56:11.883Z"
    },
    "ukmadlz": {
      "owner": "ukmadlz",
      "lastExecuted": "2023-12-07T19:50:59.410Z"
    },
    "0x90": {
      "owner": "0x90",
      "lastExecuted": "2022-02-08T02:36:43.051Z"
    },
    "danielesteban": {
      "owner": "danielesteban",
      "lastExecuted": "2022-02-08T02:36:43.051Z"
    },
    "olgabot": {
      "owner": "olgabot",
      "lastExecuted": "2022-02-08T02:36:43.051Z"
    },
    "gaearon": {
      "owner": "gaearon",
      "lastExecuted": "2022-02-08T02:36:43.051Z"
    },
    "edunham": {
      "owner": "edunham",
      "lastExecuted": "2022-02-08T02:36:43.051Z"
    },
    "jvns": {
      "owner": "jvns",
      "lastExecuted": "2022-02-08T02:36:43.051Z"
    },
    "nickytonline": {
      "owner": "nickytonline",
      "lastExecuted": "2022-02-08T02:36:43.051Z"
    },
    "bbcallen": {
      "owner": "bbcallen",
      "lastExecuted": "2022-02-08T02:36:43.051Z"
    },
    "abernix": {
      "owner": "abernix",
      "lastExecuted": "2022-02-08T02:36:43.051Z"
    },
    "negue": {
      "owner": "negue",
      "lastExecuted": "2022-02-08T02:36:43.051Z"
    },
    "brainwane": {
      "owner": "brainwane",
      "lastExecuted": "2022-02-08T02:36:43.051Z"
    },
    "jsoverson": {
      "owner": "jsoverson",
      "lastExecuted": "2022-02-08T02:36:43.051Z"
    },
    "foolnotion": {
      "owner": "foolnotion",
      "lastExecuted": "2022-02-08T02:36:43.051Z"
    },
    "Civil": {
      "owner": "Civil",
      "lastExecuted": "2022-02-08T02:36:43.051Z"
    },
    "veit": {
      "owner": "veit",
      "lastExecuted": "2022-02-08T02:36:43.051Z"
    },
    "felixturner": {
      "owner": "felixturner",
      "lastExecuted": "2022-02-08T02:36:43.051Z"
    },
    "oconnor663": {
      "owner": "oconnor663",
      "lastExecuted": "2022-02-08T02:47:47.353Z"
    },
    "mdozmorov": {
      "owner": "mdozmorov",
      "lastExecuted": "2022-02-08T02:47:47.353Z"
    },
    "bjoerge": {
      "owner": "bjoerge",
      "lastExecuted": "2022-02-08T02:47:47.353Z"
    },
    "myoung34": {
      "owner": "myoung34",
      "lastExecuted": "2022-02-08T02:47:47.353Z"
    },
    "esimov": {
      "owner": "esimov",
      "lastExecuted": "2022-02-08T02:47:47.353Z"
    },
    "iphelix": {
      "owner": "iphelix",
      "lastExecuted": "2022-02-08T02:47:47.353Z"
    },
    "rvantonder": {
      "owner": "rvantonder",
      "lastExecuted": "2022-02-08T02:47:47.353Z"
    },
    "sastraxi": {
      "owner": "sastraxi",
      "lastExecuted": "2022-02-08T02:47:47.353Z"
    },
    "HackerPoet": {
      "owner": "HackerPoet",
      "lastExecuted": "2022-02-08T02:47:47.353Z"
    },
    "korken89": {
      "owner": "korken89",
      "lastExecuted": "2022-02-08T02:47:47.353Z"
    },
    "yhaenggi": {
      "owner": "yhaenggi",
      "lastExecuted": "2022-02-08T02:47:47.353Z"
    },
    "BenTheElder": {
      "owner": "BenTheElder",
      "lastExecuted": "2022-02-08T02:47:47.353Z"
    },
    "codewithkristian": {
      "owner": "codewithkristian",
      "lastExecuted": "2022-02-08T02:47:47.353Z"
    },
    "skoren": {
      "owner": "skoren",
      "lastExecuted": "2022-02-08T02:47:47.353Z"
    },
    "joshbeitler": {
      "owner": "joshbeitler",
      "lastExecuted": "2022-02-08T02:47:47.353Z"
    },
    "keroxp": {
      "owner": "keroxp",
      "lastExecuted": "2022-02-08T02:47:47.353Z"
    },
    "Darksonn": {
      "owner": "Darksonn",
      "lastExecuted": "2022-02-08T02:47:47.353Z"
    },
    "wwwtyro": {
      "owner": "wwwtyro",
      "lastExecuted": "2022-02-08T02:47:47.353Z"
    },
    "flekschas": {
      "owner": "flekschas",
      "lastExecuted": "2022-02-08T02:47:47.353Z"
    },
    "EdCharbeneau": {
      "owner": "EdCharbeneau",
      "lastExecuted": "2022-02-08T02:47:47.353Z"
    },
    "saippuakauppias": {
      "owner": "saippuakauppias",
      "lastExecuted": "2022-02-08T02:47:47.353Z"
    },
    "notrab": {
      "owner": "notrab",
      "lastExecuted": "2022-02-08T02:54:44.826Z"
    },
    "andrasio": {
      "owner": "andrasio",
      "lastExecuted": "2022-02-08T02:54:44.826Z"
    },
    "Smolations": {
      "owner": "Smolations",
      "lastExecuted": "2022-02-08T02:54:44.826Z"
    },
    "stefanjudis": {
      "owner": "stefanjudis",
      "lastExecuted": "2022-02-08T02:54:44.826Z"
    },
    "pajlada": {
      "owner": "pajlada",
      "lastExecuted": "2022-02-08T02:54:44.826Z"
    },
    "mirceanis": {
      "owner": "mirceanis",
      "lastExecuted": "2022-02-08T02:54:44.826Z"
    },
    "wtrocki": {
      "owner": "wtrocki",
      "lastExecuted": "2022-02-08T02:54:44.826Z"
    },
    "dstotijn": {
      "owner": "dstotijn",
      "lastExecuted": "2022-02-08T02:54:44.826Z"
    },
    "h13i32maru": {
      "owner": "h13i32maru",
      "lastExecuted": "2022-02-08T02:54:44.826Z"
    },
    "snurk": {
      "owner": "snurk",
      "lastExecuted": "2022-02-08T02:54:44.826Z"
    },
    "sethgrid": {
      "owner": "sethgrid",
      "lastExecuted": "2022-02-08T02:54:44.826Z"
    },
    "coblee": {
      "owner": "coblee",
      "lastExecuted": "2022-02-08T02:54:44.826Z"
    },
    "wookayin": {
      "owner": "wookayin",
      "lastExecuted": "2022-02-08T02:54:44.826Z"
    },
    "marcograss": {
      "owner": "marcograss",
      "lastExecuted": "2022-02-08T02:54:44.826Z"
    },
    "satazor": {
      "owner": "satazor",
      "lastExecuted": "2022-02-08T02:54:44.826Z"
    },
    "shrhdk": {
      "owner": "shrhdk",
      "lastExecuted": "2022-02-08T02:54:44.826Z"
    },
    "wesleytodd": {
      "owner": "wesleytodd",
      "lastExecuted": "2022-02-08T02:54:44.826Z"
    },
    "lholmquist": {
      "owner": "lholmquist",
      "lastExecuted": "2022-02-08T02:54:44.826Z"
    },
    "crnacura": {
      "owner": "crnacura",
      "lastExecuted": "2022-02-08T02:54:44.826Z"
    },
    "SaraVieira": {
      "owner": "SaraVieira",
      "lastExecuted": "2022-02-08T02:54:44.826Z"
    },
    "CalcProgrammer1": {
      "owner": "CalcProgrammer1",
      "lastExecuted": "2022-02-08T03:02:12.816Z"
    },
    "idancali": {
      "owner": "idancali",
      "lastExecuted": "2022-02-08T03:02:12.816Z"
    },
    "privatenumber": {
      "owner": "privatenumber",
      "lastExecuted": "2022-02-08T03:02:12.816Z"
    },
    "j23414": {
      "owner": "j23414",
      "lastExecuted": "2022-02-08T03:02:12.816Z"
    },
    "dennislwm": {
      "owner": "dennislwm",
      "lastExecuted": "2022-02-08T03:02:12.816Z"
    },
    "jmkoni": {
      "owner": "jmkoni",
      "lastExecuted": "2022-02-08T03:02:12.816Z"
    },
    "davidkpiano": {
      "owner": "davidkpiano",
      "lastExecuted": "2022-02-08T03:02:12.816Z"
    },
    "Arnavion": {
      "owner": "Arnavion",
      "lastExecuted": "2022-02-08T03:02:12.816Z"
    },
    "deepu105": {
      "owner": "deepu105",
      "lastExecuted": "2022-02-08T03:02:12.816Z"
    },
    "omeraplak": {
      "owner": "omeraplak",
      "lastExecuted": "2022-02-08T03:02:12.816Z"
    },
    "nvbn": {
      "owner": "nvbn",
      "lastExecuted": "2022-02-08T03:02:12.816Z"
    },
    "eliben": {
      "owner": "eliben",
      "lastExecuted": "2022-02-08T03:02:12.816Z"
    },
    "phil-opp": {
      "owner": "phil-opp",
      "lastExecuted": "2022-02-08T03:02:12.816Z"
    },
    "danielSanchezQ": {
      "owner": "danielSanchezQ",
      "lastExecuted": "2022-02-08T03:02:12.816Z"
    },
    "OakNinja": {
      "owner": "OakNinja",
      "lastExecuted": "2022-02-08T03:02:12.816Z"
    },
    "qw3rtman": {
      "owner": "qw3rtman",
      "lastExecuted": "2022-02-08T03:02:12.816Z"
    },
    "uroboro": {
      "owner": "uroboro",
      "lastExecuted": "2022-02-08T03:02:12.816Z"
    },
    "gwillem": {
      "owner": "gwillem",
      "lastExecuted": "2022-02-08T03:02:12.816Z"
    },
    "muan": {
      "owner": "muan",
      "lastExecuted": "2022-02-08T03:02:12.816Z"
    },
    "tidwall": {
      "owner": "tidwall",
      "lastExecuted": "2022-02-08T03:09:20.946Z"
    },
    "ifiokjr": {
      "owner": "ifiokjr",
      "lastExecuted": "2022-02-08T03:09:20.946Z"
    },
    "Rich-Harris": {
      "owner": "Rich-Harris",
      "lastExecuted": "2022-02-08T03:09:20.946Z"
    },
    "ashleygwilliams": {
      "owner": "ashleygwilliams",
      "lastExecuted": "2022-02-08T03:09:20.946Z"
    },
    "bunnie": {
      "owner": "bunnie",
      "lastExecuted": "2022-02-08T03:09:20.946Z"
    },
    "nbp": {
      "owner": "nbp",
      "lastExecuted": "2022-02-08T03:09:20.946Z"
    },
    "aantonop": {
      "owner": "aantonop",
      "lastExecuted": "2022-02-08T03:09:20.946Z"
    },
    "mrnugget": {
      "owner": "mrnugget",
      "lastExecuted": "2022-02-08T03:09:20.946Z"
    },
    "liamg": {
      "owner": "liamg",
      "lastExecuted": "2022-02-08T03:09:20.946Z"
    },
    "hipstersmoothie": {
      "owner": "hipstersmoothie",
      "lastExecuted": "2022-02-08T03:09:20.946Z"
    },
    "bitoiu": {
      "owner": "bitoiu",
      "lastExecuted": "2022-02-08T03:09:20.946Z"
    },
    "cmgriffing": {
      "owner": "cmgriffing",
      "lastExecuted": "2022-02-08T03:09:20.946Z"
    },
    "jeehoonkang": {
      "owner": "jeehoonkang",
      "lastExecuted": "2022-02-08T03:09:20.946Z"
    },
    "pennycoders": {
      "owner": "pennycoders",
      "lastExecuted": "2022-02-08T03:09:20.946Z"
    },
    "lauripiispanen": {
      "owner": "lauripiispanen",
      "lastExecuted": "2022-02-08T03:09:20.946Z"
    },
    "trevorblades": {
      "owner": "trevorblades",
      "lastExecuted": "2022-02-08T03:09:20.946Z"
    },
    "sagikazarmark": {
      "owner": "sagikazarmark",
      "lastExecuted": "2022-02-08T03:09:20.946Z"
    },
    "MichaelJolley": {
      "owner": "MichaelJolley",
      "lastExecuted": "2022-02-08T03:19:25.484Z"
    },
    "romeovs": {
      "owner": "romeovs",
      "lastExecuted": "2022-02-08T03:19:25.484Z"
    },
    "ctreffs": {
      "owner": "ctreffs",
      "lastExecuted": "2022-02-08T03:19:25.484Z"
    },
    "rakannimer": {
      "owner": "rakannimer",
      "lastExecuted": "2022-02-08T03:19:25.484Z"
    },
    "ganlub": {
      "owner": "ganlub",
      "lastExecuted": "2022-02-08T03:19:25.484Z"
    },
    "nick-thompson": {
      "owner": "nick-thompson",
      "lastExecuted": "2022-02-08T03:19:25.484Z"
    },
    "romkatv": {
      "owner": "romkatv",
      "lastExecuted": "2022-02-08T03:19:25.484Z"
    },
    "prologic": {
      "owner": "prologic",
      "lastExecuted": "2022-02-08T03:19:25.484Z"
    },
    "amaurym": {
      "owner": "amaurym",
      "lastExecuted": "2022-02-08T03:19:25.484Z"
    },
    "kroitor": {
      "owner": "kroitor",
      "lastExecuted": "2022-02-08T03:19:25.484Z"
    },
    "Urigo": {
      "owner": "Urigo",
      "lastExecuted": "2022-02-08T03:19:25.484Z"
    },
    "MaxGraey": {
      "owner": "MaxGraey",
      "lastExecuted": "2022-02-08T03:19:25.484Z"
    },
    "Eloston": {
      "owner": "Eloston",
      "lastExecuted": "2022-02-08T03:19:25.484Z"
    },
    "jdanyow": {
      "owner": "jdanyow",
      "lastExecuted": "2022-02-08T03:19:25.484Z"
    },
    "kovidgoyal": {
      "owner": "kovidgoyal",
      "lastExecuted": "2022-02-08T03:19:25.484Z"
    },
    "Jeija": {
      "owner": "Jeija",
      "lastExecuted": "2022-02-08T03:19:25.484Z"
    },
    "wizkid057": {
      "owner": "wizkid057",
      "lastExecuted": "2022-02-08T03:19:25.484Z"
    },
    "jglovier": {
      "owner": "jglovier",
      "lastExecuted": "2022-02-08T03:28:24.327Z"
    },
    "MadeByMike": {
      "owner": "MadeByMike",
      "lastExecuted": "2022-02-08T03:28:24.327Z"
    },
    "tiangolo": {
      "owner": "tiangolo",
      "lastExecuted": "2022-02-08T03:28:24.327Z"
    },
    "ecooper7": {
      "owner": "ecooper7",
      "lastExecuted": "2022-02-08T03:28:24.327Z"
    },
    "morgs32": {
      "owner": "morgs32",
      "lastExecuted": "2022-02-08T03:28:24.327Z"
    },
    "sokra": {
      "owner": "sokra",
      "lastExecuted": "2022-02-08T03:28:24.327Z"
    },
    "berstend": {
      "owner": "berstend",
      "lastExecuted": "2022-02-08T03:28:24.327Z"
    },
    "notwaldorf": {
      "owner": "notwaldorf",
      "lastExecuted": "2022-02-08T03:28:24.327Z"
    },
    "drwpow": {
      "owner": "drwpow",
      "lastExecuted": "2022-02-08T03:28:24.327Z"
    },
    "katef": {
      "owner": "katef",
      "lastExecuted": "2022-02-08T03:28:24.327Z"
    },
    "archseer": {
      "owner": "archseer",
      "lastExecuted": "2022-02-08T03:28:24.327Z"
    },
    "JugglerX": {
      "owner": "JugglerX",
      "lastExecuted": "2022-02-08T03:28:24.327Z"
    },
    "peasey": {
      "owner": "peasey",
      "lastExecuted": "2022-02-08T03:28:24.327Z"
    },
    "stefanbuck": {
      "owner": "stefanbuck",
      "lastExecuted": "2022-02-08T03:28:24.327Z"
    },
    "vincentriemer": {
      "owner": "vincentriemer",
      "lastExecuted": "2022-02-08T03:28:24.327Z"
    },
    "erogol": {
      "owner": "erogol",
      "lastExecuted": "2022-02-08T03:35:24.936Z"
    },
    "fregante": {
      "owner": "fregante",
      "lastExecuted": "2022-02-08T03:35:24.936Z"
    },
    "jmhummel": {
      "owner": "jmhummel",
      "lastExecuted": "2022-02-08T03:35:24.936Z"
    },
    "mauricioabreu": {
      "owner": "mauricioabreu",
      "lastExecuted": "2022-02-08T03:35:24.936Z"
    },
    "mcornella": {
      "owner": "mcornella",
      "lastExecuted": "2022-02-08T03:35:24.936Z"
    },
    "jessfraz": {
      "owner": "jessfraz",
      "lastExecuted": "2022-02-08T03:35:24.936Z"
    },
    "torch2424": {
      "owner": "torch2424",
      "lastExecuted": "2022-02-08T03:35:24.936Z"
    },
    "valeriansaliou": {
      "owner": "valeriansaliou",
      "lastExecuted": "2022-02-08T03:35:24.936Z"
    },
    "cassidoo": {
      "owner": "cassidoo",
      "lastExecuted": "2022-02-08T03:35:24.936Z"
    },
    "wedi": {
      "owner": "wedi",
      "lastExecuted": "2022-02-08T03:35:24.936Z"
    },
    "mobily": {
      "owner": "mobily",
      "lastExecuted": "2022-02-08T03:35:24.936Z"
    },
    "lukehefson": {
      "owner": "lukehefson",
      "lastExecuted": "2022-02-08T03:35:24.936Z"
    },
    "0vercl0k": {
      "owner": "0vercl0k",
      "lastExecuted": "2022-02-08T03:35:24.936Z"
    },
    "SergioBenitez": {
      "owner": "SergioBenitez",
      "lastExecuted": "2022-02-08T03:35:24.936Z"
    },
    "HAYASAKA-Ryosuke": {
      "owner": "HAYASAKA-Ryosuke",
      "lastExecuted": "2022-02-08T03:42:03.517Z"
    },
    "paulmelnikow": {
      "owner": "paulmelnikow",
      "lastExecuted": "2022-02-08T03:42:03.517Z"
    },
    "achannarasappa": {
      "owner": "achannarasappa",
      "lastExecuted": "2022-02-08T03:42:03.517Z"
    },
    "kentcdodds": {
      "owner": "kentcdodds",
      "lastExecuted": "2022-02-08T03:42:03.517Z"
    },
    "coding-horror": {
      "owner": "coding-horror",
      "lastExecuted": "2022-02-08T03:42:03.517Z"
    },
    "LiamRandall": {
      "owner": "LiamRandall",
      "lastExecuted": "2022-02-08T03:42:03.517Z"
    },
    "gjbae1212": {
      "owner": "gjbae1212",
      "lastExecuted": "2022-02-08T03:42:03.517Z"
    },
    "schickling": {
      "owner": "schickling",
      "lastExecuted": "2022-02-08T03:42:03.517Z"
    },
    "rovo89": {
      "owner": "rovo89",
      "lastExecuted": "2022-02-08T03:42:03.517Z"
    },
    "righettod": {
      "owner": "righettod",
      "lastExecuted": "2022-02-08T03:42:03.517Z"
    },
    "hanspagel": {
      "owner": "hanspagel",
      "lastExecuted": "2022-02-08T03:42:03.517Z"
    },
    "NHDaly": {
      "owner": "NHDaly",
      "lastExecuted": "2022-02-08T03:42:03.517Z"
    },
    "mossr": {
      "owner": "mossr",
      "lastExecuted": "2022-02-08T03:42:03.517Z"
    },
    "RyanWarner": {
      "owner": "RyanWarner",
      "lastExecuted": "2022-02-08T03:48:18.349Z"
    },
    "mauriciopoppe": {
      "owner": "mauriciopoppe",
      "lastExecuted": "2022-02-08T03:48:18.349Z"
    },
    "Miffyli": {
      "owner": "Miffyli",
      "lastExecuted": "2022-02-08T03:48:18.349Z"
    },
    "ctubio": {
      "owner": "ctubio",
      "lastExecuted": "2022-02-08T03:48:18.349Z"
    },
    "mauricecruz": {
      "owner": "mauricecruz",
      "lastExecuted": "2022-02-08T03:48:18.349Z"
    },
    "Siguza": {
      "owner": "Siguza",
      "lastExecuted": "2022-02-08T03:48:18.349Z"
    },
    "bluematter": {
      "owner": "bluematter",
      "lastExecuted": "2022-02-08T03:48:18.349Z"
    },
    "ceuk": {
      "owner": "ceuk",
      "lastExecuted": "2022-02-08T03:48:18.349Z"
    },
    "una": {
      "owner": "una",
      "lastExecuted": "2022-02-08T03:48:18.349Z"
    },
    "thetutlage": {
      "owner": "thetutlage",
      "lastExecuted": "2022-02-08T03:48:18.349Z"
    },
    "alinush": {
      "owner": "alinush",
      "lastExecuted": "2022-02-08T03:48:18.349Z"
    },
    "qntm": {
      "owner": "qntm",
      "lastExecuted": "2022-02-08T03:48:18.349Z"
    },
    "axe312ger": {
      "owner": "axe312ger",
      "lastExecuted": "2022-02-08T03:54:35.097Z"
    },
    "krallin": {
      "owner": "krallin",
      "lastExecuted": "2022-02-08T03:54:35.097Z"
    },
    "alu042": {
      "owner": "alu042",
      "lastExecuted": "2022-02-08T03:54:35.097Z"
    },
    "mbbroberg": {
      "owner": "mbbroberg",
      "lastExecuted": "2022-02-08T03:54:35.097Z"
    },
    "croqaz": {
      "owner": "croqaz",
      "lastExecuted": "2022-02-08T03:54:35.097Z"
    },
    "indianajson": {
      "owner": "indianajson",
      "lastExecuted": "2022-02-08T03:54:35.097Z"
    },
    "robertlong": {
      "owner": "robertlong",
      "lastExecuted": "2022-02-08T03:54:35.097Z"
    },
    "StarpTech": {
      "owner": "StarpTech",
      "lastExecuted": "2022-02-08T03:54:35.097Z"
    },
    "dferber90": {
      "owner": "dferber90",
      "lastExecuted": "2022-02-08T03:54:35.097Z"
    },
    "vcunat": {
      "owner": "vcunat",
      "lastExecuted": "2022-02-08T03:54:35.097Z"
    },
    "tomkwok": {
      "owner": "tomkwok",
      "lastExecuted": "2022-02-08T03:54:35.097Z"
    },
    "asottile": {
      "owner": "asottile",
      "lastExecuted": "2022-02-08T04:00:42.622Z"
    },
    "Palakis": {
      "owner": "Palakis",
      "lastExecuted": "2022-02-08T04:00:42.622Z"
    },
    "krzkaczor": {
      "owner": "krzkaczor",
      "lastExecuted": "2022-02-08T04:00:42.622Z"
    },
    "copy": {
      "owner": "copy",
      "lastExecuted": "2022-02-08T04:00:42.622Z"
    },
    "adzialocha": {
      "owner": "adzialocha",
      "lastExecuted": "2022-02-08T04:00:42.622Z"
    },
    "timnugent": {
      "owner": "timnugent",
      "lastExecuted": "2022-02-08T04:00:42.622Z"
    },
    "cx20": {
      "owner": "cx20",
      "lastExecuted": "2022-02-08T04:00:42.622Z"
    },
    "davelandry": {
      "owner": "davelandry",
      "lastExecuted": "2022-02-08T04:00:42.622Z"
    },
    "donmccurdy": {
      "owner": "donmccurdy",
      "lastExecuted": "2022-02-08T04:00:42.622Z"
    },
    "lance": {
      "owner": "lance",
      "lastExecuted": "2023-12-20T08:20:26.782Z"
    },
    "dommmel": {
      "owner": "dommmel",
      "lastExecuted": "2022-02-16T09:33:44.179Z"
    },
    "MadRabbit": {
      "owner": "MadRabbit",
      "lastExecuted": "2022-03-23T23:45:23.782Z"
    },
    "jakobo": {
      "owner": "jakobo",
      "lastExecuted": "2023-12-20T08:20:26.782Z"
    },
    "ioguix": {
      "owner": "ioguix",
      "lastExecuted": "2023-12-20T08:20:26.782Z"
    },
    "wizardishungry": {
      "owner": "wizardishungry",
      "lastExecuted": "2023-12-20T08:20:26.782Z"
    },
    "kyleconroy": {
      "owner": "kyleconroy",
      "lastExecuted": "2023-12-20T09:13:35.071Z"
    },
    "brandonroberts": {
      "owner": "brandonroberts",
      "lastExecuted": "2023-12-20T09:13:35.071Z"
    },
    "wdavidw": {
      "owner": "wdavidw",
      "lastExecuted": "2023-12-20T09:19:41.764Z"
    },
    "apfrancis": {
      "owner": "apfrancis",
      "lastExecuted": "2023-12-20T09:19:41.764Z"
    },
    "akx": {
      "owner": "akx",
      "lastExecuted": "2023-12-20T09:19:41.764Z"
    },
    "shawwn": {
      "owner": "shawwn",
      "lastExecuted": "2023-12-20T09:19:41.764Z"
    },
    "antirez": {
      "owner": "antirez",
      "lastExecuted": "2023-12-20T09:19:41.764Z"
    },
    "jonasbn": {
      "owner": "jonasbn",
      "lastExecuted": "2023-12-20T09:19:41.764Z"
    },
    "marcan": {
      "owner": "marcan",
      "lastExecuted": "2023-12-20T07:19:04.989Z"
    },
    "phire": {
      "owner": "phire",
      "lastExecuted": "2023-12-20T07:43:50.101Z"
    },
    "jezhumble": {
      "owner": "jezhumble",
      "lastExecuted": "2023-12-20T08:03:05.367Z"
    },
    "cefn": {
      "owner": "cefn",
      "lastExecuted": "2023-12-20T08:03:05.367Z"
    },
    "darccio": {
      "owner": "darccio",
      "lastExecuted": "2023-12-20T08:03:05.367Z"
    },
    "bgstaal": {
      "owner": "bgstaal",
      "lastExecuted": "2023-12-20T08:03:05.367Z"
    },
    "xpn": {
      "owner": "xpn",
      "lastExecuted": "2023-12-20T08:51:32.151Z"
    },
    "bagder": {
      "owner": "bagder",
      "lastExecuted": "2023-12-20T08:51:32.151Z"
    },
    "miniBill": {
      "owner": "miniBill",
      "lastExecuted": "2023-12-20T08:51:32.151Z"
    },
    "jaretburkett": {
      "owner": "jaretburkett",
      "lastExecuted": "2023-12-20T08:51:32.151Z"
    },
    "sjhewitt": {
      "owner": "sjhewitt",
      "lastExecuted": "2023-12-20T08:51:32.151Z"
    },
    "drewm": {
      "owner": "drewm",
      "lastExecuted": "2023-12-20T10:04:22.547Z"
    },
    "karpathy": {
      "owner": "karpathy",
      "lastExecuted": "2023-12-20T10:04:22.547Z"
    },
    "catid": {
      "owner": "catid",
      "lastExecuted": "2023-12-20T10:21:23.881Z"
    },
    "benbalter": {
      "owner": "benbalter",
      "lastExecuted": "2023-12-20T10:21:23.881Z"
    },
    "rvencu": {
      "owner": "rvencu",
      "lastExecuted": "2023-12-20T10:21:23.881Z"
    },
    "jbochi": {
      "owner": "jbochi",
      "lastExecuted": "2023-12-20T10:21:23.881Z"
    },
    "keunhong": {
      "owner": "keunhong",
      "lastExecuted": "2023-12-20T10:21:23.881Z"
    },
    "michenriksen": {
      "owner": "michenriksen",
      "lastExecuted": "2023-12-20T10:21:23.881Z"
    },
    "mwaskom": {
      "owner": "mwaskom",
      "lastExecuted": "2023-12-20T10:21:23.881Z"
    },
    "Claudiu": {
      "owner": "Claudiu",
      "lastExecuted": "2023-12-20T10:21:23.881Z"
    },
    "FauxFaux": {
      "owner": "FauxFaux",
      "lastExecuted": "2023-12-20T10:27:42.860Z"
    },
    "andsens": {
      "owner": "andsens",
      "lastExecuted": "2023-12-20T10:27:42.860Z"
    },
    "mrded": {
      "owner": "mrded",
      "lastExecuted": "2023-12-20T10:27:42.860Z"
    },
    "pmowrer": {
      "owner": "pmowrer",
      "lastExecuted": "2023-12-20T08:33:05.275Z"
    },
    "peduarte": {
      "owner": "peduarte",
      "lastExecuted": "2023-12-20T08:33:05.275Z"
    },
    "jammus": {
      "owner": "jammus",
      "lastExecuted": "2023-12-20T08:33:05.275Z"
    },
    "bradfrost": {
      "owner": "bradfrost",
      "lastExecuted": "2023-12-20T08:33:05.275Z"
    },
    "mariuslundgard": {
      "owner": "mariuslundgard",
      "lastExecuted": "2023-12-20T08:33:05.275Z"
    },
    "adieyal": {
      "owner": "adieyal",
      "lastExecuted": "2023-12-20T09:05:31.107Z"
    },
    "enmand": {
      "owner": "enmand",
      "lastExecuted": "2023-12-20T09:05:31.107Z"
    },
    "lutzroeder": {
      "owner": "lutzroeder",
      "lastExecuted": "2023-12-20T09:05:31.107Z"
    },
    "BurntSushi": {
      "owner": "BurntSushi",
      "lastExecuted": "2023-12-20T09:25:51.311Z"
    },
    "altryne": {
      "owner": "altryne",
      "lastExecuted": "2023-12-20T09:32:06.582Z"
    },
    "yyx990803": {
      "owner": "yyx990803",
      "lastExecuted": "2023-12-20T09:38:21.698Z"
    },
    "michaelfester": {
      "owner": "michaelfester",
      "lastExecuted": "2023-12-20T09:44:31.224Z"
    },
    "Cr4sh": {
      "owner": "Cr4sh",
      "lastExecuted": "2023-12-20T09:44:31.224Z"
    },
    "foxyblocks": {
      "owner": "foxyblocks",
      "lastExecuted": "2023-12-20T09:57:04.019Z"
    },
    "tibi-p": {
      "owner": "tibi-p",
      "lastExecuted": "2023-12-20T09:57:04.019Z"
    },
    "harrywang": {
      "owner": "harrywang",
      "lastExecuted": "2023-12-20T10:33:52.375Z"
    },
    "JustMaier": {
      "owner": "JustMaier",
      "lastExecuted": "2023-12-20T10:39:56.801Z"
    },
    "kachkaev": {
      "owner": "kachkaev",
      "lastExecuted": "2023-12-20T10:39:56.801Z"
    },
    "mxmlnbln": {
      "owner": "mxmlnbln",
      "lastExecuted": "2023-12-14T16:04:43.890Z"
    },
    "cfchou": {
      "owner": "cfchou",
      "lastExecuted": "2023-12-06T17:41:41.823Z"
    },
    "cstork": {
      "owner": "cstork",
      "lastExecuted": "2023-12-03T17:47:45.680Z"
    },
    "tlynam": {
      "owner": "tlynam",
      "lastExecuted": "2023-12-20T10:46:19.916Z"
    },
    "adrienbrault": {
      "owner": "adrienbrault",
      "lastExecuted": "2023-12-20T10:39:56.801Z"
    },
    "yhlam": {
      "owner": "yhlam",
      "lastExecuted": "2023-12-11T18:52:53.725Z"
    },
    "juuuuuu": {
      "owner": "juuuuuu",
      "lastExecuted": "2023-12-13T05:59:47.661Z"
    },
    "nmeylan": {
      "owner": "nmeylan",
      "lastExecuted": "2023-12-20T10:46:19.916Z"
    },
    "PixiBixi": {
      "owner": "PixiBixi",
      "lastExecuted": "2023-12-20T10:46:19.916Z"
    },
    "andrei-shabanski": {
      "owner": "andrei-shabanski",
      "lastExecuted": "2023-12-20T10:46:19.916Z"
    },
    "wouitmil": {
      "owner": "wouitmil",
      "lastExecuted": "2023-12-20T10:46:19.916Z"
    },
    "derhuerst": {
      "owner": "derhuerst",
      "lastExecuted": "2023-12-14T16:56:43.953Z"
    },
    "vigneshgurusamy": {
      "owner": "vigneshgurusamy",
      "lastExecuted": "2023-12-20T10:46:19.916Z"
    },
    "arturmoreira": {
      "owner": "arturmoreira",
      "lastExecuted": "2023-12-20T10:46:19.916Z"
    },
    "brightwheel": {
      "owner": "brightwheel",
      "lastExecuted": "2023-12-20T10:46:19.916Z"
    },
    "maesbri": {
      "owner": "maesbri",
      "lastExecuted": "2023-12-20T10:46:19.916Z"
    },
    "billmask": {
      "owner": "billmask",
      "lastExecuted": "2023-12-18T06:00:16.133Z"
    },
    "bucuracak": {
      "owner": "bucuracak",
      "lastExecuted": "2023-12-02T00:35:44.101Z"
    },
    "daniel-luberda": {
      "owner": "daniel-luberda",
      "lastExecuted": "2023-12-13T05:59:47.661Z"
    },
    "konzinov": {
      "owner": "konzinov",
      "lastExecuted": "2023-12-13T05:59:47.661Z"
    },
    "tgachet": {
      "owner": "tgachet",
      "lastExecuted": "2023-12-20T10:46:19.916Z"
    },
    "damienfern": {
      "owner": "damienfern",
      "lastExecuted": "2023-12-20T10:46:19.916Z"
    },
    "ahmadateya": {
      "owner": "ahmadateya",
      "lastExecuted": "2023-12-20T10:46:19.916Z"
    },
    "18829525501": {
      "owner": "18829525501",
      "lastExecuted": "2023-12-11T17:45:16.218Z"
    },
    "naveencom": {
      "owner": "naveencom",
      "lastExecuted": "2023-12-14T16:04:43.890Z"
    },
    "kayhill": {
      "owner": "kayhill",
      "lastExecuted": "2023-12-14T12:03:20.149Z"
    },
    "rfronk-ssdt": {
      "owner": "rfronk-ssdt",
      "lastExecuted": "2023-12-14T12:03:20.149Z"
    },
    "hasnat-we": {
      "owner": "hasnat-we",
      "lastExecuted": "2023-12-19T13:49:50.449Z"
    },
    "jquesnelle": {
      "owner": "jquesnelle",
      "lastExecuted": "2023-12-20T07:50:00.105Z"
    },
    "anchan828": {
      "owner": "anchan828",
      "lastExecuted": "2023-12-20T07:56:08.149Z"
    },
    "Aaron-ML": {
      "owner": "Aaron-ML",
      "lastExecuted": "2023-12-20T10:46:19.916Z"
    },
    "mistadikay": {
      "owner": "mistadikay",
      "lastExecuted": "2023-12-09T20:38:11.993Z"
    },
    "senthil28": {
      "owner": "senthil28",
      "lastExecuted": "2023-12-20T10:46:19.916Z"
    },
    "darold": {
      "owner": "darold",
      "lastExecuted": "2023-12-20T09:50:43.070Z"
    },
    "baggids": {
      "owner": "baggids",
      "lastExecuted": "2023-12-20T10:46:19.916Z"
    },
    "elucian": {
      "owner": "elucian",
      "lastExecuted": "2023-12-09T20:50:33.110Z"
    },
    "atournayre": {
      "owner": "atournayre",
      "lastExecuted": "2023-12-20T10:46:19.916Z"
    },
    "dsferruzza": {
      "owner": "dsferruzza",
      "lastExecuted": "2023-12-20T10:46:19.916Z"
    },
    "nathanieltalbot": {
      "owner": "nathanieltalbot",
      "lastExecuted": "2023-12-20T10:46:19.916Z"
    },
    "mkaladi": {
      "owner": "mkaladi",
      "lastExecuted": "2023-12-20T10:46:19.916Z"
    },
    "WadeFade": {
      "owner": "WadeFade",
      "lastExecuted": "2023-12-20T10:46:19.916Z"
    },
    "kulaginds": {
      "owner": "kulaginds",
      "lastExecuted": "2023-12-20T10:46:19.916Z"
    },
    "Yodo92": {
      "owner": "Yodo92",
      "lastExecuted": "2023-12-20T10:46:19.916Z"
    },
    "SebSept": {
      "owner": "SebSept",
      "lastExecuted": "2023-12-20T10:46:19.916Z"
    },
    "maxhelias": {
      "owner": "maxhelias",
      "lastExecuted": "2023-12-20T10:46:19.916Z"
    },
    "AidanKlark": {
      "owner": "AidanKlark",
      "lastExecuted": "2023-12-20T10:46:19.916Z"
    },
    "AlexanderKurenkov": {
      "owner": "AlexanderKurenkov",
      "lastExecuted": "2023-12-20T10:46:19.916Z"
    },
    "hobin-kang": {
      "owner": "hobin-kang",
      "lastExecuted": "2023-12-20T10:46:19.916Z"
    },
    "qferr": {
      "owner": "qferr",
      "lastExecuted": "2023-12-20T10:46:19.916Z"
    }
  }
}